{
  "required": true,
  "minVersion": "0.8",
  "package": "kgg.translator.mixin",
  "compatibilityLevel": "JAVA_17",
  "mixins": [
    "DrawContextMixinTooltip",
    "ScreenMixinForChat",
    "screen.BookEditScreenMixin",
    "world.EntityRendererMixin",
    "world.SignTextMixin",
    "world.TextDisplayEntityMixin"
  ],
  "client": [
    "DrawContextMixinScreenText",
    "hud.BossBarHudMixin",
    "hud.ChatHudMixin",
    "hud.ChatScreenMixin",
    "hud.InGameHudForScoreboardMixin",
    "hud.InGameHudForTitleMixin",
    "screen.BookScreenMixin",
    "world.SignBlockEntityRendererMixin"
  ],
  "injectors": {
    "defaultRequire": 1
  }
}
